simplemath_ganesh/__init__.py
simplemath_ganesh/math_ops.py
simplemath_giri-0.0.1.dist-info/METADATA
simplemath_giri-0.0.1.dist-info/WHEEL
simplemath_giri-0.0.1.dist-info/top_level.txt
simplemath_giri-0.0.1.dist-info/RECORD
