Metadata-Version: 2.4
Name: simplemath-giri
Version: 0.0.1
Summary: A very simple math library
Author: Ganesh kinkar Giri
License: MIT
Requires-Python: >=3.8
